robo_app/__init__.py
robo_app/application.py
robo_app/constants.py
robo_app/controller.py
robo_app/models.py
robo_app/network.py
robo_app/robot_util.py
robo_app/util.py
robo_app/views.py
robo_app/widgets.py
robot_executor-0.1.2.dist-info/LICENSE
robot_executor-0.1.2.dist-info/METADATA
robot_executor-0.1.2.dist-info/WHEEL
robot_executor-0.1.2.dist-info/entry_points.txt
robot_executor-0.1.2.dist-info/top_level.txt
robot_executor-0.1.2.dist-info/RECORD
